vitrage/__init__.py
vitrage/i18n.py
vitrage/keystone_client.py
vitrage/messaging.py
vitrage/opts.py
vitrage/os_clients.py
vitrage/rpc.py
vitrage/api/__init__.py
vitrage/api/app.py
vitrage/api/app.wsgi
vitrage/api/hooks.py
vitrage/api/policy.py
vitrage/api/controllers/__init__.py
vitrage/api/controllers/rest.py
vitrage/api/controllers/root.py
vitrage/api/controllers/v1/__init__.py
vitrage/api/controllers/v1/alarm.py
vitrage/api/controllers/v1/alarm_base.py
vitrage/api/controllers/v1/count.py
vitrage/api/controllers/v1/event.py
vitrage/api/controllers/v1/history.py
vitrage/api/controllers/v1/rca.py
vitrage/api/controllers/v1/resource.py
vitrage/api/controllers/v1/root.py
vitrage/api/controllers/v1/service.py
vitrage/api/controllers/v1/status.py
vitrage/api/controllers/v1/template.py
vitrage/api/controllers/v1/topology.py
vitrage/api/controllers/v1/webhook.py
vitrage/api_handler/__init__.py
vitrage/api_handler/apis/__init__.py
vitrage/api_handler/apis/alarm.py
vitrage/api_handler/apis/base.py
vitrage/api_handler/apis/event.py
vitrage/api_handler/apis/operational.py
vitrage/api_handler/apis/rca.py
vitrage/api_handler/apis/resource.py
vitrage/api_handler/apis/template.py
vitrage/api_handler/apis/topology.py
vitrage/api_handler/apis/webhook.py
vitrage/cli/__init__.py
vitrage/cli/api.py
vitrage/cli/graph.py
vitrage/cli/machine_learning.py
vitrage/cli/notifier.py
vitrage/cli/persistor.py
vitrage/cli/snmp_parsing.py
vitrage/cli/status.py
vitrage/cli/storage.py
vitrage/common/__init__.py
vitrage/common/config.py
vitrage/common/constants.py
vitrage/common/exception.py
vitrage/common/utils.py
vitrage/common/policies/__init__.py
vitrage/common/policies/alarms.py
vitrage/common/policies/base.py
vitrage/common/policies/event.py
vitrage/common/policies/rca.py
vitrage/common/policies/resource.py
vitrage/common/policies/service.py
vitrage/common/policies/status.py
vitrage/common/policies/template.py
vitrage/common/policies/topology.py
vitrage/common/policies/webhook.py
vitrage-15.0.1.dist-info/METADATA
vitrage-15.0.1.dist-info/WHEEL
vitrage-15.0.1.dist-info/entry_points.txt
vitrage-15.0.1.dist-info/pbr.json
vitrage-15.0.1.dist-info/top_level.txt
vitrage-15.0.1.dist-info/RECORD
